{"metadata": {"dbt_schema_version": "https://schemas.getdbt.com/dbt/run-results/v4.json", "dbt_version": "1.5.9", "generated_at": "2024-02-03T05:26:44.266626Z", "invocation_id": "c0eba0c3-73c3-4013-bbe7-e254d7861cb3", "env": {}}, "results": [{"status": "success", "timing": [{"name": "compile", "started_at": "2024-02-03T05:26:31.350832Z", "completed_at": "2024-02-03T05:26:31.404291Z"}, {"name": "execute", "started_at": "2024-02-03T05:26:31.411376Z", "completed_at": "2024-02-03T05:26:35.541379Z"}], "thread_id": "Thread-1 (worker)", "execution_time": 4.209703683853149, "adapter_response": {"_message": "CREATE TABLE (10.0 rows, 19.2 MiB processed)", "code": "CREATE TABLE", "rows_affected": 10, "bytes_processed": 20127647, "bytes_billed": 20971520, "location": "US", "project_id": "airflow-412610", "job_id": "afa3281a-0ce2-4698-adc8-30c6b3fe3e48", "slot_ms": 763}, "message": "CREATE TABLE (10.0 rows, 19.2 MiB processed)", "failures": null, "unique_id": "model.retail.report_customer_invoices"}, {"status": "success", "timing": [{"name": "compile", "started_at": "2024-02-03T05:26:35.570797Z", "completed_at": "2024-02-03T05:26:35.622281Z"}, {"name": "execute", "started_at": "2024-02-03T05:26:35.627409Z", "completed_at": "2024-02-03T05:26:39.710804Z"}], "thread_id": "Thread-1 (worker)", "execution_time": 4.150709629058838, "adapter_response": {"_message": "CREATE TABLE (10.0 rows, 17.0 MiB processed)", "code": "CREATE TABLE", "rows_affected": 10, "bytes_processed": 17831344, "bytes_billed": 20971520, "location": "US", "project_id": "airflow-412610", "job_id": "1328fc74-c85c-4159-85da-4377ac1288f6", "slot_ms": 1037}, "message": "CREATE TABLE (10.0 rows, 17.0 MiB processed)", "failures": null, "unique_id": "model.retail.report_product_invoices"}, {"status": "success", "timing": [{"name": "compile", "started_at": "2024-02-03T05:26:39.745682Z", "completed_at": "2024-02-03T05:26:39.774406Z"}, {"name": "execute", "started_at": "2024-02-03T05:26:39.779856Z", "completed_at": "2024-02-03T05:26:44.235313Z"}], "thread_id": "Thread-1 (worker)", "execution_time": 4.498041868209839, "adapter_response": {"_message": "CREATE TABLE (13.0 rows, 12.4 MiB processed)", "code": "CREATE TABLE", "rows_affected": 13, "bytes_processed": 13049402, "bytes_billed": 20971520, "location": "US", "project_id": "airflow-412610", "job_id": "dcec9e8f-1305-47a5-84af-8eb850415bfe", "slot_ms": 1013}, "message": "CREATE TABLE (13.0 rows, 12.4 MiB processed)", "failures": null, "unique_id": "model.retail.report_year_invoices"}], "elapsed_time": 14.719820261001587, "args": {"populate_cache": true, "favor_state": false, "send_anonymous_usage_stats": true, "strict_mode": false, "version_check": true, "vars": {}, "warn_error_options": {"include": [], "exclude": []}, "log_format": "default", "log_level_file": "debug", "select": ["path:models/report"], "log_file_max_bytes": 10485760, "macro_debugging": false, "print": true, "write_json": true, "log_path": "/usr/local/airflow/include/dbt/logs", "enable_legacy_logger": false, "use_colors_file": true, "printer_width": 80, "defer": false, "profiles_dir": "/usr/local/airflow/include/dbt/", "cache_selected_only": false, "exclude": [], "introspect": true, "use_colors": true, "quiet": false, "which": "run", "log_format_file": "debug", "static_parser": true, "project_dir": "/usr/local/airflow/include/dbt", "indirect_selection": "eager", "partial_parse": true, "log_level": "info"}}